{
	"match": {
		"competition": "National League",
		"date": "Saturday 24th September 2016",
		"time": "12:15:00",
		"status": "Full Time",
		"teams": [
			{
				"side": "home",
				"no": "68",
				"name": "Wrexham",
				"halfTimeScore": "0",
				"score": "0",
				"players": [
					{
						"shirtNo": "1",
						"name": "Shwan Jalal"
					},
					{
						"shirtNo": "11",
						"name": "Sean Newton"
					},
					{
						"shirtNo": "5",
						"name": "Martin Riley"
					},
					{
						"shirtNo": "4",
						"name": "Hamza Bencherif"
					},
					{
						"shirtNo": "10",
						"name": "John Rooney",
						"caution": {
							"minute": "42"
						}
					},
					{
						"shirtNo": "6",
						"name": "Curtis Tilt"
					},
					{
						"shirtNo": "13",
						"name": "Mark Carrington",
						"caution": {
							"minute": "80"
						}
					},
					{
						"shirtNo": "14",
						"name": "Paul Rutherford",
						"substitution": {
							"replacedBy": "Callum Powell",
							"minute": "82"
						}
					},
					{
						"shirtNo": "15",
						"name": "Rob Evans",
						"caution": {
							"minute": "14"
						}
					},
					{
						"shirtNo": "18",
						"name": "Shaun Harrad",
						"substitution": {
							"replacedBy": "Jordan Evans",
							"minute": "38"
						}
					},
					{
						"shirtNo": "34",
						"name": "Michael Bakare",
						"substitution": {
							"replacedBy": "Gerry McDonagh",
							"minute": "90"
						}
					},
					{
						"shirtNo": "12",
						"name": "Kai Edwards"
					},
					{
						"shirtNo": "16",
						"name": "Jordan Evans"
					},
					{
						"shirtNo": "17",
						"name": "Callum Powell"
					},
					{
						"shirtNo": "20",
						"name": "Gerry McDonagh"
					},
					{
						"shirtNo": "29",
						"name": "Tyler Harvey"
					}
				]
			},
			{
				"side": "away",
				"no": "1004",
				"name": "Chester",
				"halfTimeScore": "0",
				"score": "0",
				"players": [
					{
						"shirtNo": "13",
						"name": "Liam Roberts"
					},
					{
						"shirtNo": "17",
						"name": "Theo Vassell"
					},
					{
						"shirtNo": "5",
						"name": "Blaine Hudson"
					},
					{
						"shirtNo": "8",
						"name": "Tom Shaw"
					},
					{
						"shirtNo": "16",
						"name": "Johnny Hunt",
						"caution": {
							"minute": "90"
						}
					},
					{
						"shirtNo": "6",
						"name": "Ryan Astles",
						"caution": {
							"minute": "90"
						}
					},
					{
						"shirtNo": "10",
						"name": "Elliott Durrell",
						"substitution": {
							"replacedBy": "Sam Hughes",
							"minute": "90"
						}
					},
					{
						"shirtNo": "21",
						"name": "Ryan Lloyd"
					},
					{
						"shirtNo": "7",
						"name": "Craig Mahon"
					},
					{
						"shirtNo": "9",
						"name": "James Alabi",
						"substitution": {
							"replacedBy": "Jordan Chapell",
							"minute": "79"
						}
					},
					{
						"shirtNo": "15",
						"name": "Kane Richards",
						"substitution": {
							"replacedBy": "Oluwaseun Akintunde",
							"minute": "90"
						}
					},
					{
						"shirtNo": "3",
						"name": "Evan Horwood"
					},
					{
						"shirtNo": "4",
						"name": "Luke George"
					},
					{
						"shirtNo": "11",
						"name": "Jordan Chapell"
					},
					{
						"shirtNo": "12",
						"name": "Sam Hughes"
					},
					{
						"shirtNo": "20",
						"name": "Oluwaseun Akintunde"
					}
				]
			}
		],
		"attendance": "5058",
		"venue": "Racecourse Ground"
	}
}

