{
	"match": {
		"competition": "National League",
		"date": "Tuesday 13th September 2016",
		"time": "19:45:00",
		"status": "Full Time",
		"teams": [
			{
				"side": "home",
				"no": "154",
				"name": "Sutton United",
				"halfTimeScore": "1",
				"score": "1",
				"goals": [
					{
						"goal": "Nicky Bailey (pen 35')"
					}
				],
				"players": [
					{
						"shirtNo": "1",
						"name": "Ross Worner",
						"caution": {
							"minute": "45"
						}
					},
					{
						"shirtNo": "2",
						"name": "Kevin Amankwaah"
					},
					{
						"shirtNo": "3",
						"name": "Daniel Wishart",
						"caution": {
							"minute": "24"
						}
					},
					{
						"shirtNo": "11",
						"name": "Ross Stearn"
					},
					{
						"shirtNo": "6",
						"name": "Jamie Collins"
					},
					{
						"shirtNo": "8",
						"name": "Bedsente Gomis",
						"substitution": {
							"replacedBy": "Maxime Biamou",
							"minute": "61"
						}
					},
					{
						"shirtNo": "7",
						"name": "Bradley Hudson-Odoi",
						"substitution": {
							"replacedBy": "Roarie Deacon",
							"minute": "61"
						}
					},
					{
						"shirtNo": "5",
						"name": "Louis John"
					},
					{
						"shirtNo": "19",
						"name": "Chris Dickson"
					},
					{
						"shirtNo": "15",
						"name": "Craig Eastmond",
						"substitution": {
							"replacedBy": "Ryan Burge",
							"minute": "72"
						}
					},
					{
						"shirtNo": "16",
						"name": "Nicky Bailey"
					},
					{
						"shirtNo": "10",
						"name": "Dan Fitchett"
					},
					{
						"shirtNo": "17",
						"name": "Daniel Spence"
					},
					{
						"shirtNo": "21",
						"name": "Roarie Deacon"
					},
					{
						"shirtNo": "23",
						"name": "Ryan Burge"
					},
					{
						"shirtNo": "24",
						"name": "Maxime Biamou"
					}
				]
			},
			{
				"side": "away",
				"no": "226",
				"name": "Braintree Town",
				"halfTimeScore": "1",
				"score": "2",
				"goals": [
					{
						"goal": "Chez Isaac (pen 45')"
					},
					{
						"goal": "Chez Isaac (90')"
					}
				],
				"players": [
					{
						"shirtNo": "22",
						"name": "Sam Beasant"
					},
					{
						"shirtNo": "3",
						"name": "Jerome Okimo"
					},
					{
						"shirtNo": "5",
						"name": "Ian Gayle",
						"caution": {
							"minute": "19"
						},
						"sendingOff": {
							"minute": "85"
						}
					},
					{
						"shirtNo": "20",
						"name": "Sam Come",
						"caution": {
							"minute": "27"
						}
					},
					{
						"shirtNo": "11",
						"name": "Craig Braham-Barrett",
						"caution": {
							"minute": "83"
						}
					},
					{
						"shirtNo": "18",
						"name": "Jake Goodman",
						"substitution": {
							"replacedBy": "Jon Ashton",
							"minute": "45"
						}
					},
					{
						"shirtNo": "8",
						"name": "Chez Isaac"
					},
					{
						"shirtNo": "15",
						"name": "Sam Matthews",
						"substitution": {
							"replacedBy": "Joe Maybanks",
							"minute": "82"
						}
					},
					{
						"shirtNo": "10",
						"name": "Simeon Akinola"
					},
					{
						"shirtNo": "16",
						"name": "Brandon Goodship",
						"substitution": {
							"replacedBy": "Lee Barnard",
							"minute": "59"
						}
					},
					{
						"shirtNo": "23",
						"name": "Michael Cheek"
					},
					{
						"shirtNo": "2",
						"name": "Barney Williams"
					},
					{
						"shirtNo": "4",
						"name": "Harry Lee"
					},
					{
						"shirtNo": "6",
						"name": "Jon Ashton"
					},
					{
						"shirtNo": "9",
						"name": "Lee Barnard"
					},
					{
						"shirtNo": "12",
						"name": "Joe Maybanks"
					}
				]
			}
		],
		"attendance": "922",
		"venue": "Borough Sports Ground"
	}
}

