{
	"match": {
		"competition": "National League",
		"date": "Saturday 6th August 2016",
		"time": "15:00:00",
		"status": "Full Time",
		"teams": [
			{
				"side": "home",
				"no": "113",
				"name": "Woking",
				"score": "1",
				"goals": [
					{
						"goal": "Ismail Yakubu (46')"
					}
				],
				"players": [
					{
						"shirtNo": "1",
						"name": "Michael Poke"
					},
					{
						"shirtNo": "2",
						"name": "Jake Caprice"
					},
					{
						"shirtNo": "3",
						"name": "Ben Gordon",
						"substitution": {
							"replacedBy": "Max Kretzschmar",
							"minute": "78"
						}
					},
					{
						"shirtNo": "8",
						"name": "Kieran Murtagh"
					},
					{
						"shirtNo": "5",
						"name": "Brian Saah",
						"caution": {
							"minute": "80"
						}
					},
					{
						"shirtNo": "4",
						"name": "Joseph Jones",
						"caution": {
							"minute": "36"
						}
					},
					{
						"shirtNo": "11",
						"name": "Nathan Ralph"
					},
					{
						"shirtNo": "14",
						"name": "Fabio Saraiva",
						"substitution": {
							"replacedBy": "Ismail Yakubu",
							"minute": "46"
						}
					},
					{
						"shirtNo": "16",
						"name": "Dennon Lewis",
						"substitution": {
							"replacedBy": "Charlie Penny",
							"minute": "68"
						}
					},
					{
						"shirtNo": "9",
						"name": "Gozie Ugwu"
					},
					{
						"shirtNo": "10",
						"name": "Zak Ansah"
					},
					{
						"shirtNo": "18",
						"name": "Brandon Hall"
					},
					{
						"shirtNo": "6",
						"name": "Ismail Yakubu"
					},
					{
						"shirtNo": "7",
						"name": "Charlie Penny"
					},
					{
						"shirtNo": "15",
						"name": "Max Kretzschmar"
					},
					{
						"shirtNo": "21",
						"name": "Luke Chike Kandi"
					}
				]
			},
			{
				"side": "away",
				"no": "79",
				"name": "Lincoln City",
				"score": "3",
				"goals": [
					{
						"goal": "Adam Marriott (28')"
					},
					{
						"goal": "Matt Rhead (60')"
					},
					{
						"goal": "Matt Rhead (pen 73')"
					}
				],
				"players": [
					{
						"shirtNo": "1",
						"name": "Paul Farman"
					},
					{
						"shirtNo": "2",
						"name": "Bradley Wood"
					},
					{
						"shirtNo": "3",
						"name": "Sam Habergham",
						"caution": {
							"minute": "70"
						}
					},
					{
						"shirtNo": "28",
						"name": "Nathan Arnold",
						"substitution": {
							"replacedBy": "Taylor Miles",
							"minute": "83"
						}
					},
					{
						"shirtNo": "18",
						"name": "Lee Beevers"
					},
					{
						"shirtNo": "5",
						"name": "Luke Waterfall"
					},
					{
						"shirtNo": "27",
						"name": "Jamie McCombe",
						"caution": {
							"minute": "56"
						}
					},
					{
						"shirtNo": "30",
						"name": "Alex Woodyard"
					},
					{
						"shirtNo": "7",
						"name": "Jack Muldoon"
					},
					{
						"shirtNo": "10",
						"name": "Adam Marriott",
						"substitution": {
							"replacedBy": "Jonathon Margetts",
							"minute": "68"
						}
					},
					{
						"shirtNo": "9",
						"name": "Matt Rhead"
					},
					{
						"shirtNo": "6",
						"name": "Callum Howe"
					},
					{
						"shirtNo": "12",
						"name": "Jonathon Margetts"
					},
					{
						"shirtNo": "14",
						"name": "Taylor Miles",
						"caution": {
							"minute": "83"
						}
					},
					{
						"shirtNo": "17",
						"name": "Elliot Hodge"
					},
					{
						"shirtNo": "25",
						"name": "Sean Raggett"
					}
				]
			}
		],
		"attendance": "1592",
		"venue": "The Laithwaite Community Stadium"
	}
}

